simplreg/__init__.py
simplreg/evaluation.py
simplreg/model_training.py
simplreg/preprocessing.py
simplreg/utils.py
simplreg/visualization.py
simplreg-0.2.dist-info/METADATA
simplreg-0.2.dist-info/WHEEL
simplreg-0.2.dist-info/top_level.txt
simplreg-0.2.dist-info/RECORD
