Metadata-Version: 2.1
Name: simplreg
Version: 0.2
Summary: A simple machine learning package for forecasting and classification
Home-page: https://github.com/Spinachboul/simplreg
Author: Mridul
Author-email: jain.mridul.20@gmail.com
Requires-Dist: pandas
Requires-Dist: numpy
Requires-Dist: scikit-learn
Requires-Dist: tabulate
Requires-Dist: matplotlib
Requires-Dist: seaborn
